oauth/__init__.py
oauth/admin.py
oauth/apps.py
oauth/models.py
oauth/tests.py
oauth/urls.py
oauth/views.py
oauth/migrations/0001_initial.py
oauth/migrations/__init__.py
oauth/python/oauth/__init__.py
oauth/python/oauth/forms.py
oauth/python/utils/core_utils.py
oauth/python/utils/cpf_validate.py
oauth/python/utils/custom_messages.py
oauth/python/utils/help.py
oauth/python/utils/send_mail.py
oauth/python/utils/teste_api.py
oauth/static/css/oauth.css
oauth/templates/oauth/base-auth.html
oauth/templates/oauth/change-password.html
oauth/templates/oauth/login.html
oauth/templates/oauth/register.html
oauth/templates/oauth/restore-passwd.html
oauth/templates/oauth/update.html
oautth-0.1.dist-info/LICENSE
oautth-0.1.dist-info/METADATA
oautth-0.1.dist-info/WHEEL
oautth-0.1.dist-info/top_level.txt
oautth-0.1.dist-info/RECORD
