Metadata-Version: 2.1
Name: oautth
Version: 0.1
Summary: App to user login, register and restore password
Home-page: https://github.com/jarnunes
Author: Jardel Nunes
Author-email: jarnunesc@gmail.com
License: MIT License
Platform: UNKNOWN
Classifier: Environment :: Web Environment
Classifier: Framework :: Django :: 4.0
Classifier: Intended Audience :: Developers
Classifier: License :: OSI Approved :: MIT License
Classifier: Operating System :: OS Independent
Classifier: Programming Language :: Python :: 3.10
Requires-Python: >=3.10
License-File: LICENSE
Requires-Dist: Django (>=4.0)
